woom/__init__.py
woom/_version.py
woom/cli.py
woom/conf.py
woom/env.py
woom/ext.py
woom/hosts.cfg
woom/hosts.ini
woom/hosts.py
woom/iters.py
woom/job.py
woom/log.py
woom/render.py
woom/tasks.ini
woom/tasks.py
woom/util.py
woom/workflow.ini
woom/workflow.py
woom/templates/env.sh
woom/templates/job.sh
woom/tests/test_util.py
woom-2025.10.1.dist-info/licenses/LICENSE
woom-2025.10.1.dist-info/METADATA
woom-2025.10.1.dist-info/WHEEL
woom-2025.10.1.dist-info/entry_points.txt
woom-2025.10.1.dist-info/top_level.txt
woom-2025.10.1.dist-info/RECORD
